aave_python
