Metadata-Version: 2.1
Name: aave-python
Version: 0.1.3
Summary: An unofficial Python3.9+ package that wraps Aave staking smart contracts
Home-page: https://github.com/PathX-Projects/Aave-DeFi-Client
Author: Harrison Schick
Author-email: hschickdevs@gmail.com
License: UNKNOWN
Platform: UNKNOWN
